ColorBurst/ColorBurst.py
ColorBurst/LISCENCE.md
ColorBurst/__init__.py
ColorBurst/classes.py
ChromaticColorBurst-1.0.3.dist-info/METADATA
ChromaticColorBurst-1.0.3.dist-info/WHEEL
ChromaticColorBurst-1.0.3.dist-info/top_level.txt
ChromaticColorBurst-1.0.3.dist-info/RECORD
