Metadata-Version: 2.1
Name: ChromaticColorBurst
Version: 1.0.3
Summary: You can now print styled TEXT to console/terminal without much of a hassel
Home-page: https://github.com/sachin-acharya-projects/ColorBurst
Author: Sachin Acharya
Author-email: acharyaraj71+ColorBurst@gmail.com
Keywords: colored_text console terminal style styled_text
Classifier: Programming Language :: Python :: 3
Classifier: License :: OSI Approved :: MIT License
Classifier: Operating System :: OS Independent
